runcode/__init__.py
runcode/runner.py
runcode_sample/__init__.py
runcode_sample/asgi.py
runcode_sample/settings.py
runcode_sample/urls.py
runcode_sample/views.py
runcode_sample/wsgi.py
runcode-0.2.1.dist-info/LICENSE
runcode-0.2.1.dist-info/METADATA
runcode-0.2.1.dist-info/WHEEL
runcode-0.2.1.dist-info/top_level.txt
runcode-0.2.1.dist-info/RECORD
