Metadata-Version: 2.1
Name: runcode
Version: 0.2.1
Summary: RunCode Python API
Home-page: https://github.com/runcode-io/runcode-python
Author: RunCode
Author-email: hello@runcode.io
License: UNKNOWN
Project-URL: Bug Tracker, https://github.com/runcode-io/runcode-python/issues
Platform: UNKNOWN
Classifier: Intended Audience :: Developers
Classifier: Operating System :: OS Independent
Classifier: License :: OSI Approved :: MIT License
Classifier: Programming Language :: Python
Classifier: Programming Language :: Python :: 3
Classifier: Programming Language :: Python :: 3.3
Classifier: Programming Language :: Python :: 3.4
Classifier: Programming Language :: Python :: 3.5
Classifier: Programming Language :: Python :: 3.6
Classifier: Programming Language :: Python :: 3.7
Classifier: Programming Language :: Python :: 3.8
Classifier: Programming Language :: Python :: 3.9
Classifier: Topic :: Software Development :: Internationalization
License-File: LICENSE
Requires-Dist: requests
